odoo/addons/purchase_rfq_number/README.rst
odoo/addons/purchase_rfq_number/__init__.py
odoo/addons/purchase_rfq_number/__manifest__.py
odoo/addons/purchase_rfq_number/data/ir_sequence_data.xml
odoo/addons/purchase_rfq_number/i18n/es.po
odoo/addons/purchase_rfq_number/i18n/purchase_rfq_number.pot
odoo/addons/purchase_rfq_number/models/__init__.py
odoo/addons/purchase_rfq_number/models/purchase_order.py
odoo/addons/purchase_rfq_number/models/res_company.py
odoo/addons/purchase_rfq_number/readme/CONFIGURE.rst
odoo/addons/purchase_rfq_number/readme/CONTRIBUTORS.rst
odoo/addons/purchase_rfq_number/readme/CREDITS.rst
odoo/addons/purchase_rfq_number/readme/DESCRIPTION.rst
odoo/addons/purchase_rfq_number/reports/purchase_report_templates.xml
odoo/addons/purchase_rfq_number/static/description/icon.png
odoo/addons/purchase_rfq_number/static/description/index.html
odoo/addons/purchase_rfq_number/tests/__init__.py
odoo/addons/purchase_rfq_number/tests/test_purchase_order.py
odoo/addons/purchase_rfq_number/views/purchase_views.xml
odoo/addons/purchase_rfq_number/views/res_config_settings_views.xml
odoo_addon_purchase_rfq_number-15.0.1.0.1.2.dist-info/METADATA
odoo_addon_purchase_rfq_number-15.0.1.0.1.2.dist-info/WHEEL
odoo_addon_purchase_rfq_number-15.0.1.0.1.2.dist-info/top_level.txt
odoo_addon_purchase_rfq_number-15.0.1.0.1.2.dist-info/RECORD
